smart_rest_client/__init__.py
smart_rest_client/base.py
smart_rest_client/client.py
smart_rest_client/exceptions.py
smart_rest_client/factories.py
smart_rest_client/settings.py
smart_rest_client/status.py
smart_rest_client/utils.py
smart_rest_client/validators.py
smart_rest_client/version.py
smart_rest_client-0.4.3.dist-info/LICENSE
smart_rest_client-0.4.3.dist-info/METADATA
smart_rest_client-0.4.3.dist-info/WHEEL
smart_rest_client-0.4.3.dist-info/top_level.txt
smart_rest_client-0.4.3.dist-info/RECORD
