Metadata-Version: 2.1
Name: smart-rest-client
Version: 0.4.3
Summary: Python wrapper to perform requests to Rest APIs using objects to request endpoints and their methods
Home-page: https://github.com/rhenter/smart-rest-client
Author: Rafael Henter
Author-email: rafael@henter.com.br
License: UNKNOWN
Keywords: rest api client python
Platform: UNKNOWN
Classifier: Development Status :: 4 - Beta
Classifier: Intended Audience :: Developers
Classifier: License :: OSI Approved :: MIT License
Classifier: Programming Language :: Python :: 3.7
Classifier: Programming Language :: Python :: 3.8
Classifier: Programming Language :: Python :: 3.9
Classifier: Topic :: Software Development :: Libraries
Requires-Dist: pysimplemodel (==2.3.3)
Requires-Dist: requests
Requires-Dist: unipath
